{"mean":{"confidence_interval":{"confidence_level":0.95,"lower_bound":3722.6552092814954,"upper_bound":3747.060470516643},"point_estimate":3733.5019396269513,"standard_error":6.265356814988704},"median":{"confidence_interval":{"confidence_level":0.95,"lower_bound":3714.6678719008264,"upper_bound":3725.9542342000814},"point_estimate":3722.693375516529,"standard_error":3.10579595284676},"median_abs_dev":{"confidence_interval":{"confidence_level":0.95,"lower_bound":20.77716014212378,"upper_bound":32.19041786656261},"point_estimate":27.914018820291428,"standard_error":3.0378751830490525},"slope":{"confidence_interval":{"confidence_level":0.95,"lower_bound":3718.893313933542,"upper_bound":3738.8199112655852},"point_estimate":3727.810988666031,"standard_error":5.09195598187756},"std_dev":{"confidence_interval":{"confidence_level":0.95,"lower_bound":28.58471920994016,"upper_bound":92.02016623969517},"point_estimate":62.95501239355755,"standard_error":16.808687162383542}}